pytest_reporting/__init__.py
pytest_reporting/behaviors.py
pytest_reporting/colors.py
pytest_reporting/fixtures.py
pytest_reporting/plugin.py
pytest_reporting/session.py
pytest_reporting-0.1.0.dist-info/LICENSE
pytest_reporting-0.1.0.dist-info/METADATA
pytest_reporting-0.1.0.dist-info/WHEEL
pytest_reporting-0.1.0.dist-info/entry_points.txt
pytest_reporting-0.1.0.dist-info/top_level.txt
pytest_reporting-0.1.0.dist-info/RECORD
