Metadata-Version: 2.1
Name: pytest-reporting
Version: 0.1.0
Summary: A plugin to report summarized results in a table format
Home-page: https://gitlab.com/too-many-programmers/pytest-reporting
Author: Benjamin Rigaud
Author-email: ben.open.source@gmail.com
Maintainer: Benjamin Rigaud
Maintainer-email: ben.open.source@gmail.com
License: MIT
Platform: UNKNOWN
Classifier: Development Status :: 4 - Beta
Classifier: Framework :: Pytest
Classifier: Intended Audience :: Developers
Classifier: Topic :: Software Development :: Testing
Classifier: Programming Language :: Python
Classifier: Programming Language :: Python :: 2
Classifier: Programming Language :: Python :: 2.7
Classifier: Programming Language :: Python :: 3
Classifier: Programming Language :: Python :: 3.5
Classifier: Programming Language :: Python :: 3.6
Classifier: Programming Language :: Python :: 3.7
Classifier: Programming Language :: Python :: Implementation :: CPython
Classifier: Programming Language :: Python :: Implementation :: PyPy
Classifier: Operating System :: OS Independent
Classifier: License :: OSI Approved :: MIT License
Requires-Python: >=2.7, !=3.0.*, !=3.1.*, !=3.2.*, !=3.3.*, !=3.4.*
Requires-Dist: pytest (>=3.5.0)
Requires-Dist: colorama (==0.4.1)
Requires-Dist: terminaltables (==3.1.0)
